odoo/addons/mrp_subcontracting_skip_no_negative/README.rst
odoo/addons/mrp_subcontracting_skip_no_negative/__init__.py
odoo/addons/mrp_subcontracting_skip_no_negative/__manifest__.py
odoo/addons/mrp_subcontracting_skip_no_negative/i18n/es.po
odoo/addons/mrp_subcontracting_skip_no_negative/i18n/it.po
odoo/addons/mrp_subcontracting_skip_no_negative/i18n/mrp_subcontracting_skip_no_negative.pot
odoo/addons/mrp_subcontracting_skip_no_negative/models/__init__.py
odoo/addons/mrp_subcontracting_skip_no_negative/models/stock_move.py
odoo/addons/mrp_subcontracting_skip_no_negative/readme/CONTRIBUTORS.rst
odoo/addons/mrp_subcontracting_skip_no_negative/readme/DESCRIPTION.rst
odoo/addons/mrp_subcontracting_skip_no_negative/static/description/icon.png
odoo/addons/mrp_subcontracting_skip_no_negative/static/description/index.html
odoo/addons/mrp_subcontracting_skip_no_negative/tests/__init__.py
odoo/addons/mrp_subcontracting_skip_no_negative/tests/test_mrp_subcontracting_skip_no_negative.py
odoo14_addon_mrp_subcontracting_skip_no_negative-14.0.1.0.1.dist-info/METADATA
odoo14_addon_mrp_subcontracting_skip_no_negative-14.0.1.0.1.dist-info/WHEEL
odoo14_addon_mrp_subcontracting_skip_no_negative-14.0.1.0.1.dist-info/top_level.txt
odoo14_addon_mrp_subcontracting_skip_no_negative-14.0.1.0.1.dist-info/RECORD
