Metadata-Version: 2.1
Name: odoo14-addon-mrp_subcontracting_skip_no_negative
Version: 14.0.1.0.1
Summary: MRP Subcontracting Skip No Negative
Home-page: https://github.com/OCA/manufacture
Author: Quartile Limited, Odoo Community Association (OCA)
Author-email: support@odoo-community.org
License: AGPL-3
Classifier: Programming Language :: Python
Classifier: Framework :: Odoo
Classifier: Framework :: Odoo :: 14.0
Classifier: License :: OSI Approved :: GNU Affero General Public License v3
Requires-Python: >=3.6
Requires-Dist: odoo14-addon-stock-no-negative
Requires-Dist: odoo<14.1dev,>=14.0a
